ShoubashouDaiNiGodotYouxiKaifaDiyiDanLingJichuRumenAnliFlappybirdFix1/README.md
ShoubashouDaiNiGodotYouxiKaifaDiyiDanLingJichuRumenAnliFlappybirdFix1/__init__.py
ShoubashouDaiNiGodotYouxiKaifaDiyiDanLingJichuRumenAnliFlappybirdFix1/__main__.py
ShoubashouDaiNiGodotYouxiKaifaDiyiDanLingJichuRumenAnliFlappybirdFix1/file.epub
ShoubashouDaiNiGodotYouxiKaifaDiyiDanLingJichuRumenAnliFlappybirdFix1/index.html
ShoubashouDaiNiGodotYouxiKaifaDiyiDanLingJichuRumenAnliFlappybirdFix1/css/__init__.py
ShoubashouDaiNiGodotYouxiKaifaDiyiDanLingJichuRumenAnliFlappybirdFix1/css/annotations.css
ShoubashouDaiNiGodotYouxiKaifaDiyiDanLingJichuRumenAnliFlappybirdFix1/css/main.css
ShoubashouDaiNiGodotYouxiKaifaDiyiDanLingJichuRumenAnliFlappybirdFix1/css/normalize.css
ShoubashouDaiNiGodotYouxiKaifaDiyiDanLingJichuRumenAnliFlappybirdFix1/css/popup.css
ShoubashouDaiNiGodotYouxiKaifaDiyiDanLingJichuRumenAnliFlappybirdFix1/font/__init__.py
ShoubashouDaiNiGodotYouxiKaifaDiyiDanLingJichuRumenAnliFlappybirdFix1/font/fontello.eot
ShoubashouDaiNiGodotYouxiKaifaDiyiDanLingJichuRumenAnliFlappybirdFix1/font/fontello.svg
ShoubashouDaiNiGodotYouxiKaifaDiyiDanLingJichuRumenAnliFlappybirdFix1/font/fontello.ttf
ShoubashouDaiNiGodotYouxiKaifaDiyiDanLingJichuRumenAnliFlappybirdFix1/font/fontello.woff
ShoubashouDaiNiGodotYouxiKaifaDiyiDanLingJichuRumenAnliFlappybirdFix1/img/__init__.py
ShoubashouDaiNiGodotYouxiKaifaDiyiDanLingJichuRumenAnliFlappybirdFix1/img/annotator-glyph-sprite.png
ShoubashouDaiNiGodotYouxiKaifaDiyiDanLingJichuRumenAnliFlappybirdFix1/img/annotator-icon-sprite.png
ShoubashouDaiNiGodotYouxiKaifaDiyiDanLingJichuRumenAnliFlappybirdFix1/img/apple-touch-icon.png
ShoubashouDaiNiGodotYouxiKaifaDiyiDanLingJichuRumenAnliFlappybirdFix1/img/cancelfullscreen.png
ShoubashouDaiNiGodotYouxiKaifaDiyiDanLingJichuRumenAnliFlappybirdFix1/img/close.png
ShoubashouDaiNiGodotYouxiKaifaDiyiDanLingJichuRumenAnliFlappybirdFix1/img/fullscreen.png
shoubashou_dai_ni_godot_youxi_kaifa_diyi_dan_ling_jichu_rumen_anli_flappybird_fix1-2025.3.24.1.dist-info/METADATA
shoubashou_dai_ni_godot_youxi_kaifa_diyi_dan_ling_jichu_rumen_anli_flappybird_fix1-2025.3.24.1.dist-info/WHEEL
shoubashou_dai_ni_godot_youxi_kaifa_diyi_dan_ling_jichu_rumen_anli_flappybird_fix1-2025.3.24.1.dist-info/entry_points.txt
shoubashou_dai_ni_godot_youxi_kaifa_diyi_dan_ling_jichu_rumen_anli_flappybird_fix1-2025.3.24.1.dist-info/top_level.txt
shoubashou_dai_ni_godot_youxi_kaifa_diyi_dan_ling_jichu_rumen_anli_flappybird_fix1-2025.3.24.1.dist-info/RECORD
