Metadata-Version: 2.1
Name: shoubashou-dai-ni-godot-youxi-kaifa-diyi-dan-ling-jichu-rumen-anli-flappybird-fix1
Version: 2025.3.24.1
Summary: 【手把手带你Godot游戏开发 第一弹】零基础入门案例：FlappyBird
Home-page: https://github.com/apachecn/shoubashou-dai-ni-godot-youxi-kaifa-diyi-dan-ling-jichu-rumen-anli-flappybird-fix1
Author: ApacheCN
Author-email: apachecn@163.com
Classifier: Development Status :: 4 - Beta
Classifier: Environment :: Console
Classifier: Intended Audience :: Developers
Classifier: Intended Audience :: End Users/Desktop
Classifier: License :: Other/Proprietary License
Classifier: Natural Language :: Chinese (Simplified)
Classifier: Natural Language :: English
Classifier: Operating System :: OS Independent
Classifier: Programming Language :: Python :: 3
Classifier: Programming Language :: Python :: 3 :: Only
Classifier: Programming Language :: Python :: 3.6
Classifier: Programming Language :: Python :: 3.7
Classifier: Topic :: Text Processing :: Markup :: Markdown
Classifier: Topic :: Text Processing :: Markup :: HTML
Classifier: Topic :: Internet :: WWW/HTTP
Classifier: Topic :: Software Development :: Documentation
Classifier: Topic :: Documentation
Requires-Python: >=3.6
